COPYING
MANIFEST.in
README.md
development.txt
requirements.txt
setup.cfg
setup.py
steadymark/__init__.py
steadymark/core.py
steadymark/runner.py
steadymark/version.py
steadymark.egg-info/PKG-INFO
steadymark.egg-info/SOURCES.txt
steadymark.egg-info/dependency_links.txt
steadymark.egg-info/entry_points.txt
steadymark.egg-info/requires.txt
steadymark.egg-info/top_level.txt