Metadata-Version: 2.1
Name: steadymark
Version: 0.8.2
Summary: Markdown-based test runner for python. Good for github projects
Home-page: http://github.com/gabrielfalcao/steadymark
Author: Gabriel Falcao
Author-email: gabriel@nacaolivre.org
License: UNKNOWN
Platform: UNKNOWN
Classifier: Development Status :: 5 - Production/Stable
Classifier: Operating System :: POSIX
Classifier: Programming Language :: Python :: 3.6
Classifier: Programming Language :: Python :: 3.7
Classifier: License :: OSI Approved :: MIT License
